{"839611105764855809": {"lat": null, "lon": null, "location": "lynn,ma", "tweet_id": 839611105764855809, "content": "Fmr Secret Service Agent Turns On Obama to Blow Wiretapping Conspiracy Wide Open https://t.co/CMSfcMnL0j", "user": 176552555, "raw_source": {"created_at": "Wed Mar 08 22:57:41 +0000 2017", "id": 839611105764855809, "id_str": "839611105764855809", "text": "Fmr Secret Service Agent Turns On Obama to Blow Wiretapping Conspiracy Wide Open https://t.co/CMSfcMnL0j", "truncated": false, "entities": {"hashtags": [], "symbols": [], "user_mentions": [], "urls": [{"url": "https://t.co/CMSfcMnL0j", "expanded_url": "http://fb.me/QyLieYJt", "display_url": "fb.me/QyLieYJt", "indices": [81, 104]}]}, "metadata": {"iso_language_code": "en", "result_type": "recent"}, "source": "<a href=\"http://www.facebook.com/twitter\" rel=\"nofollow\">Facebook</a>", "in_reply_to_status_id": null, "in_reply_to_status_id_str": null, "in_reply_to_user_id": null, "in_reply_to_user_id_str": null, "in_reply_to_screen_name": null, "user": {"id": 176552555, "id_str": "176552555", "name": "paul duncan", "screen_name": "pdunc1013", "location": "lynn,ma", "description": "Syracuse graduate, Consultant, From NY, like Yankees, Travel, Golf, Fish and Birds. Lutheran", "url": "https://t.co/l43wGpWYx5", "entities": {"url": {"urls": [{"url": "https://t.co/l43wGpWYx5", "expanded_url": "http://bettershopping.com", "display_url": "bettershopping.com", "indices": [0, 23]}]}, "description": {"urls": []}}, "protected": false, "followers_count": 634, "friends_count": 2115, "listed_count": 39, "created_at": "Mon Aug 09 21:08:04 +0000 2010", "favourites_count": 596, "utc_offset": null, "time_zone": null, "geo_enabled": true, "verified": false, "statuses_count": 114622, "lang": "en", "contributors_enabled": false, "is_translator": false, "is_translation_enabled": false, "profile_background_color": "C0DEED", "profile_background_image_url": "http://abs.twimg.com/images/themes/theme1/bg.png", "profile_background_image_url_https": "https://abs.twimg.com/images/themes/theme1/bg.png", "profile_background_tile": false, "profile_image_url": "http://pbs.twimg.com/profile_images/473831966794469377/Z4GDlkC6_normal.png", "profile_image_url_https": "https://pbs.twimg.com/profile_images/473831966794469377/Z4GDlkC6_normal.png", "profile_banner_url": "https://pbs.twimg.com/profile_banners/176552555/1401805482", "profile_link_color": "1DA1F2", "profile_sidebar_border_color": "C0DEED", "profile_sidebar_fill_color": "DDEEF6", "profile_text_color": "333333", "profile_use_background_image": true, "has_extended_profile": true, "default_profile": true, "default_profile_image": false, "following": null, "follow_request_sent": null, "notifications": null, "translator_type": "none"}, "geo": null, "coordinates": null, "place": null, "contributors": null, "is_quote_status": false, "retweet_count": 0, "favorite_count": 0, "favorited": false, "retweeted": false, "possibly_sensitive": false, "lang": "en"}, "data_point": "none", "time": "Wed Mar 08 22:57:41 +0000 2017"}, "839611082545197057": {"lat": null, "lon": null, "location": "Boston, MA", "tweet_id": 839611082545197057, "content": "@NancyPelosi @HouseGOP STOP WITH THE LIES YOU ARE TRYING TO DEFLECT OBAMA HAVING A SLUSH FUND AND USED AMERICANS TAX DOLLARS TO DO IT!", "user": 808011260528852998, "raw_source": {"created_at": "Wed Mar 08 22:57:35 +0000 2017", "id": 839611082545197057, "id_str": "839611082545197057", "text": "@NancyPelosi @HouseGOP STOP WITH THE LIES YOU ARE TRYING TO DEFLECT OBAMA HAVING A SLUSH FUND AND USED AMERICANS TAX DOLLARS TO DO IT!", "truncated": false, "entities": {"hashtags": [], "symbols": [], "user_mentions": [{"screen_name": "NancyPelosi", "name": "Nancy Pelosi", "id": 15764644, "id_str": "15764644", "indices": [0, 12]}, {"screen_name": "HouseGOP", "name": "House Republicans", "id": 15207668, "id_str": "15207668", "indices": [13, 22]}], "urls": []}, "metadata": {"iso_language_code": "en", "result_type": "recent"}, "source": "<a href=\"http://twitter.com\" rel=\"nofollow\">Twitter Web Client</a>", "in_reply_to_status_id": 839564471735619586, "in_reply_to_status_id_str": "839564471735619586", "in_reply_to_user_id": 15764644, "in_reply_to_user_id_str": "15764644", "in_reply_to_screen_name": "NancyPelosi", "user": {"id": 808011260528852998, "id_str": "808011260528852998", "name": "kerria kelly", "screen_name": "kerriakelly71", "location": "Boston, MA", "description": "", "url": null, "entities": {"description": {"urls": []}}, "protected": false, "followers_count": 3, "friends_count": 50, "listed_count": 0, "created_at": "Sun Dec 11 18:11:11 +0000 2016", "favourites_count": 0, "utc_offset": null, "time_zone": null, "geo_enabled": false, "verified": false, "statuses_count": 490, "lang": "en", "contributors_enabled": false, "is_translator": false, "is_translation_enabled": false, "profile_background_color": "F5F8FA", "profile_background_image_url": null, "profile_background_image_url_https": null, "profile_background_tile": false, "profile_image_url": "http://abs.twimg.com/sticky/default_profile_images/default_profile_2_normal.png", "profile_image_url_https": "https://abs.twimg.com/sticky/default_profile_images/default_profile_2_normal.png", "profile_link_color": "1DA1F2", "profile_sidebar_border_color": "C0DEED", "profile_sidebar_fill_color": "DDEEF6", "profile_text_color": "333333", "profile_use_background_image": true, "has_extended_profile": true, "default_profile": true, "default_profile_image": true, "following": null, "follow_request_sent": null, "notifications": null, "translator_type": "none"}, "geo": null, "coordinates": null, "place": null, "contributors": null, "is_quote_status": false, "retweet_count": 0, "favorite_count": 0, "favorited": false, "retweeted": false, "lang": "en"}, "data_point": "none", "time": "Wed Mar 08 22:57:35 +0000 2017"}, "839610247358599173": {"lat": null, "lon": null, "location": "Sharon, MA", "tweet_id": 839610247358599173, "content": "Obama is livid over Trumps charge. Obama is a wolf in sheep's clothing. His presidency was a one big lie and half the nation knows it.", "user": 1662767858, "raw_source": {"created_at": "Wed Mar 08 22:54:16 +0000 2017", "id": 839610247358599173, "id_str": "839610247358599173", "text": "Obama is livid over Trumps charge. Obama is a wolf in sheep's clothing. His presidency was a one big lie and half the nation knows it.", "truncated": false, "entities": {"hashtags": [], "symbols": [], "user_mentions": [], "urls": []}, "metadata": {"iso_language_code": "en", "result_type": "recent"}, "source": "<a href=\"http://twitter.com/download/iphone\" rel=\"nofollow\">Twitter for iPhone</a>", "in_reply_to_status_id": null, "in_reply_to_status_id_str": null, "in_reply_to_user_id": null, "in_reply_to_user_id_str": null, "in_reply_to_screen_name": null, "user": {"id": 1662767858, "id_str": "1662767858", "name": "Mendy", "screen_name": "mendy721", "location": "Sharon, MA", "description": "", "url": null, "entities": {"description": {"urls": []}}, "protected": false, "followers_count": 11, "friends_count": 1, "listed_count": 1, "created_at": "Sun Aug 11 15:03:48 +0000 2013", "favourites_count": 8, "utc_offset": -14400, "time_zone": "Atlantic Time (Canada)", "geo_enabled": false, "verified": false, "statuses_count": 4165, "lang": "en", "contributors_enabled": false, "is_translator": false, "is_translation_enabled": false, "profile_background_color": "C0DEED", "profile_background_image_url": "http://abs.twimg.com/images/themes/theme1/bg.png", "profile_background_image_url_https": "https://abs.twimg.com/images/themes/theme1/bg.png", "profile_background_tile": false, "profile_image_url": "http://abs.twimg.com/sticky/default_profile_images/default_profile_3_normal.png", "profile_image_url_https": "https://abs.twimg.com/sticky/default_profile_images/default_profile_3_normal.png", "profile_link_color": "1DA1F2", "profile_sidebar_border_color": "C0DEED", "profile_sidebar_fill_color": "DDEEF6", "profile_text_color": "333333", "profile_use_background_image": true, "has_extended_profile": false, "default_profile": true, "default_profile_image": true, "following": null, "follow_request_sent": null, "notifications": null, "translator_type": "none"}, "geo": null, "coordinates": null, "place": null, "contributors": null, "is_quote_status": false, "retweet_count": 0, "favorite_count": 0, "favorited": false, "retweeted": false, "lang": "en"}, "data_point": "none", "time": "Wed Mar 08 22:54:16 +0000 2017"}, "839609693643264000": {"lat": null, "lon": null, "location": "Boston, MA", "tweet_id": 839609693643264000, "content": "@CharaCarbone @realDonaldTrump @RandPaul I agree. Don't be like Obama and create a healthcare system he himself didn't even use.", "user": 244590973, "raw_source": {"created_at": "Wed Mar 08 22:52:04 +0000 2017", "id": 839609693643264000, "id_str": "839609693643264000", "text": "@CharaCarbone @realDonaldTrump @RandPaul I agree. Don't be like Obama and create a healthcare system he himself didn't even use.", "truncated": false, "entities": {"hashtags": [], "symbols": [], "user_mentions": [{"screen_name": "CharaCarbone", "name": "Il Volo\u2764Is The Best", "id": 714871998, "id_str": "714871998", "indices": [0, 13]}, {"screen_name": "realDonaldTrump", "name": "Donald J. Trump", "id": 25073877, "id_str": "25073877", "indices": [14, 30]}, {"screen_name": "RandPaul", "name": "Senator Rand Paul", "id": 216881337, "id_str": "216881337", "indices": [31, 40]}], "urls": []}, "metadata": {"iso_language_code": "en", "result_type": "recent"}, "source": "<a href=\"https://mobile.twitter.com\" rel=\"nofollow\">Mobile Web (M5)</a>", "in_reply_to_status_id": 839607281675350016, "in_reply_to_status_id_str": "839607281675350016", "in_reply_to_user_id": 714871998, "in_reply_to_user_id_str": "714871998", "in_reply_to_screen_name": "CharaCarbone", "user": {"id": 244590973, "id_str": "244590973", "name": "Anthony Gilbert", "screen_name": "keepTHEfaith341", "location": "Boston, MA", "description": "First and foremost, a Christian.... Boston Sports....Stop wishing and start doing... University of Belichick...\nKatie Nolan is my dream girl", "url": null, "entities": {"description": {"urls": []}}, "protected": false, "followers_count": 97, "friends_count": 438, "listed_count": 3, "created_at": "Sat Jan 29 17:24:18 +0000 2011", "favourites_count": 968, "utc_offset": null, "time_zone": null, "geo_enabled": false, "verified": false, "statuses_count": 6710, "lang": "en", "contributors_enabled": false, "is_translator": false, "is_translation_enabled": false, "profile_background_color": "000000", "profile_background_image_url": "http://abs.twimg.com/images/themes/theme1/bg.png", "profile_background_image_url_https": "https://abs.twimg.com/images/themes/theme1/bg.png", "profile_background_tile": false, "profile_image_url": "http://pbs.twimg.com/profile_images/537395063236464641/RbfblZy9_normal.jpeg", "profile_image_url_https": "https://pbs.twimg.com/profile_images/537395063236464641/RbfblZy9_normal.jpeg", "profile_banner_url": "https://pbs.twimg.com/profile_banners/244590973/1447830804", "profile_link_color": "DD2E44", "profile_sidebar_border_color": "000000", "profile_sidebar_fill_color": "000000", "profile_text_color": "000000", "profile_use_background_image": false, "has_extended_profile": false, "default_profile": false, "default_profile_image": false, "following": null, "follow_request_sent": null, "notifications": null, "translator_type": "none"}, "geo": null, "coordinates": null, "place": null, "contributors": null, "is_quote_status": false, "retweet_count": 0, "favorite_count": 1, "favorited": false, "retweeted": false, "lang": "en"}, "data_point": "none", "time": "Wed Mar 08 22:52:04 +0000 2017"}, "839609666527236097": {"lat": null, "lon": null, "location": "Boston, MA", "tweet_id": 839609666527236097, "content": "Senator Sessions Was Targeted To Deflect From Massive Obama DOJ Slush Fund https://t.co/vpI0e6AzFG via @YouTube", "user": 808011260528852998, "raw_source": {"created_at": "Wed Mar 08 22:51:58 +0000 2017", "id": 839609666527236097, "id_str": "839609666527236097", "text": "Senator Sessions Was Targeted To Deflect From Massive Obama DOJ Slush Fund https://t.co/vpI0e6AzFG via @YouTube", "truncated": false, "entities": {"hashtags": [], "symbols": [], "user_mentions": [{"screen_name": "YouTube", "name": "YouTube", "id": 10228272, "id_str": "10228272", "indices": [103, 111]}], "urls": [{"url": "https://t.co/vpI0e6AzFG", "expanded_url": "https://youtu.be/h3_nLmfpwCc", "display_url": "youtu.be/h3_nLmfpwCc", "indices": [75, 98]}]}, "metadata": {"iso_language_code": "en", "result_type": "recent"}, "source": "<a href=\"http://twitter.com\" rel=\"nofollow\">Twitter Web Client</a>", "in_reply_to_status_id": null, "in_reply_to_status_id_str": null, "in_reply_to_user_id": null, "in_reply_to_user_id_str": null, "in_reply_to_screen_name": null, "user": {"id": 808011260528852998, "id_str": "808011260528852998", "name": "kerria kelly", "screen_name": "kerriakelly71", "location": "Boston, MA", "description": "", "url": null, "entities": {"description": {"urls": []}}, "protected": false, "followers_count": 3, "friends_count": 50, "listed_count": 0, "created_at": "Sun Dec 11 18:11:11 +0000 2016", "favourites_count": 0, "utc_offset": null, "time_zone": null, "geo_enabled": false, "verified": false, "statuses_count": 490, "lang": "en", "contributors_enabled": false, "is_translator": false, "is_translation_enabled": false, "profile_background_color": "F5F8FA", "profile_background_image_url": null, "profile_background_image_url_https": null, "profile_background_tile": false, "profile_image_url": "http://abs.twimg.com/sticky/default_profile_images/default_profile_2_normal.png", "profile_image_url_https": "https://abs.twimg.com/sticky/default_profile_images/default_profile_2_normal.png", "profile_link_color": "1DA1F2", "profile_sidebar_border_color": "C0DEED", "profile_sidebar_fill_color": "DDEEF6", "profile_text_color": "333333", "profile_use_background_image": true, "has_extended_profile": true, "default_profile": true, "default_profile_image": true, "following": null, "follow_request_sent": null, "notifications": null, "translator_type": "none"}, "geo": null, "coordinates": null, "place": null, "contributors": null, "is_quote_status": false, "retweet_count": 0, "favorite_count": 0, "favorited": false, "retweeted": false, "possibly_sensitive": false, "lang": "en"}, "data_point": "none", "time": "Wed Mar 08 22:51:58 +0000 2017"}, "839609499535167488": {"lat": null, "lon": null, "location": "Kentucky \u27a1\ufe0f Kansas", "tweet_id": 839609499535167488, "content": "RT @BostonGlobe: These new photos from the National Park Service show Obama\u2019s inauguration crowd was bigger than Trump\u2019s: https://t.co/L41u\u2026", "user": 469981380, "raw_source": {"created_at": "Wed Mar 08 22:51:18 +0000 2017", "id": 839609499535167488, "id_str": "839609499535167488", "text": "RT @BostonGlobe: These new photos from the National Park Service show Obama\u2019s inauguration crowd was bigger than Trump\u2019s: https://t.co/L41u\u2026", "truncated": false, "entities": {"hashtags": [], "symbols": [], "user_mentions": [{"screen_name": "BostonGlobe", "name": "The Boston Globe", "id": 95431448, "id_str": "95431448", "indices": [3, 15]}], "urls": []}, "metadata": {"iso_language_code": "en", "result_type": "recent"}, "source": "<a href=\"http://twitter.com/download/iphone\" rel=\"nofollow\">Twitter for iPhone</a>", "in_reply_to_status_id": null, "in_reply_to_status_id_str": null, "in_reply_to_user_id": null, "in_reply_to_user_id_str": null, "in_reply_to_screen_name": null, "user": {"id": 469981380, "id_str": "469981380", "name": "Trent Catilla", "screen_name": "_catilla", "location": "Kentucky \u27a1\ufe0f Kansas", "description": "Always God\u2019s boy! Alumni of WKU - Go CARDS - Go PATS - Go TOPS", "url": null, "entities": {"description": {"urls": []}}, "protected": false, "followers_count": 508, "friends_count": 685, "listed_count": 4, "created_at": "Sat Jan 21 06:08:29 +0000 2012", "favourites_count": 4850, "utc_offset": -25200, "time_zone": "Mountain Time (US & Canada)", "geo_enabled": false, "verified": false, "statuses_count": 11369, "lang": "en", "contributors_enabled": false, "is_translator": false, "is_translation_enabled": false, "profile_background_color": "131516", "profile_background_image_url": "http://pbs.twimg.com/profile_background_images/410711174/198550_1637717381852_1204260294_31615444_3833481_n.jpg", "profile_background_image_url_https": "https://pbs.twimg.com/profile_background_images/410711174/198550_1637717381852_1204260294_31615444_3833481_n.jpg", "profile_background_tile": true, "profile_image_url": "http://pbs.twimg.com/profile_images/834165283388551169/l1d7lsLu_normal.jpg", "profile_image_url_https": "https://pbs.twimg.com/profile_images/834165283388551169/l1d7lsLu_normal.jpg", "profile_banner_url": "https://pbs.twimg.com/profile_banners/469981380/1474242302", "profile_link_color": "990000", "profile_sidebar_border_color": "EEEEEE", "profile_sidebar_fill_color": "EFEFEF", "profile_text_color": "333333", "profile_use_background_image": true, "has_extended_profile": true, "default_profile": false, "default_profile_image": false, "following": null, "follow_request_sent": null, "notifications": null, "translator_type": "none"}, "geo": null, "coordinates": null, "place": null, "contributors": null, "retweeted_status": {"created_at": "Wed Mar 08 04:31:05 +0000 2017", "id": 839332622576795648, "id_str": "839332622576795648", "text": "These new photos from the National Park Service show Obama\u2019s inauguration crowd was bigger than Trump\u2019s:\u2026 https://t.co/QnnrnDC6Y2", "truncated": true, "entities": {"hashtags": [], "symbols": [], "user_mentions": [], "urls": [{"url": "https://t.co/QnnrnDC6Y2", "expanded_url": "https://twitter.com/i/web/status/839332622576795648", "display_url": "twitter.com/i/web/status/8\u2026", "indices": [106, 129]}]}, "metadata": {"iso_language_code": "en", "result_type": "recent"}, "source": "<a href=\"http://www.socialflow.com\" rel=\"nofollow\">SocialFlow</a>", "in_reply_to_status_id": null, "in_reply_to_status_id_str": null, "in_reply_to_user_id": null, "in_reply_to_user_id_str": null, "in_reply_to_screen_name": null, "user": {"id": 95431448, "id_str": "95431448", "name": "The Boston Globe", "screen_name": "BostonGlobe", "location": "Boston, MA", "description": "Boston and New England's leading source for breaking news and analysis, with coverage from across the world. Follow our journalists: https://t.co/KPOiZTQG87", "url": "http://t.co/g2XphqdJIo", "entities": {"url": {"urls": [{"url": "http://t.co/g2XphqdJIo", "expanded_url": "http://bostonglobe.com", "display_url": "bostonglobe.com", "indices": [0, 22]}]}, "description": {"urls": [{"url": "https://t.co/KPOiZTQG87", "expanded_url": "https://twitter.com/BostonGlobe/lists/globe-journalists", "display_url": "twitter.com/BostonGlobe/li\u2026", "indices": [133, 156]}]}}, "protected": false, "followers_count": 609760, "friends_count": 1236, "listed_count": 9633, "created_at": "Tue Dec 08 14:33:38 +0000 2009", "favourites_count": 330, "utc_offset": -18000, "time_zone": "Eastern Time (US & Canada)", "geo_enabled": true, "verified": true, "statuses_count": 226335, "lang": "en", "contributors_enabled": false, "is_translator": false, "is_translation_enabled": false, "profile_background_color": "EDECE9", "profile_background_image_url": "http://pbs.twimg.com/profile_background_images/378800000003877254/c79663e95d0e284ce165db703dffd474.jpeg", "profile_background_image_url_https": "https://pbs.twimg.com/profile_background_images/378800000003877254/c79663e95d0e284ce165db703dffd474.jpeg", "profile_background_tile": false, "profile_image_url": "http://pbs.twimg.com/profile_images/586570157734019072/Qxz1LIIM_normal.png", "profile_image_url_https": "https://pbs.twimg.com/profile_images/586570157734019072/Qxz1LIIM_normal.png", "profile_banner_url": "https://pbs.twimg.com/profile_banners/95431448/1486691881", "profile_link_color": "050505", "profile_sidebar_border_color": "FFFFFF", "profile_sidebar_fill_color": "FFFFFF", "profile_text_color": "000000", "profile_use_background_image": true, "has_extended_profile": false, "default_profile": false, "default_profile_image": false, "following": null, "follow_request_sent": null, "notifications": null, "translator_type": "regular"}, "geo": null, "coordinates": null, "place": null, "contributors": null, "is_quote_status": false, "retweet_count": 69, "favorite_count": 114, "favorited": false, "retweeted": false, "possibly_sensitive": false, "lang": "en"}, "is_quote_status": false, "retweet_count": 69, "favorite_count": 0, "favorited": false, "retweeted": false, "lang": "en"}, "data_point": "none", "time": "Wed Mar 08 22:51:18 +0000 2017"}, "839609343880413185": {"lat": null, "lon": null, "location": "Illinois, USA", "tweet_id": 839609343880413185, "content": "RT @vivacioususa: @BarackObama @MichelleObama Mr. Obama, you and Michelle are the classic examples of CLASS! \ud83d\udc4d\ud83c\udffeThank you for respecting all\u2026", "user": 826447087139246080, "raw_source": {"created_at": "Wed Mar 08 22:50:41 +0000 2017", "id": 839609343880413185, "id_str": "839609343880413185", "text": "RT @vivacioususa: @BarackObama @MichelleObama Mr. Obama, you and Michelle are the classic examples of CLASS! \ud83d\udc4d\ud83c\udffeThank you for respecting all\u2026", "truncated": false, "entities": {"hashtags": [], "symbols": [], "user_mentions": [{"screen_name": "vivacioususa", "name": "Countmyblessings\ud83d\ude4f", "id": 823762852481732608, "id_str": "823762852481732608", "indices": [3, 16]}, {"screen_name": "BarackObama", "name": "Barack Obama", "id": 813286, "id_str": "813286", "indices": [18, 30]}, {"screen_name": "MichelleObama", "name": "Michelle Obama", "id": 409486555, "id_str": "409486555", "indices": [31, 45]}], "urls": []}, "metadata": {"iso_language_code": "en", "result_type": "recent"}, "source": "<a href=\"http://twitter.com/download/iphone\" rel=\"nofollow\">Twitter for iPhone</a>", "in_reply_to_status_id": null, "in_reply_to_status_id_str": null, "in_reply_to_user_id": null, "in_reply_to_user_id_str": null, "in_reply_to_screen_name": null, "user": {"id": 826447087139246080, "id_str": "826447087139246080", "name": "Horst Seehofer", "screen_name": "christsoziale", "location": "Illinois, USA", "description": "Millions of people within and outside the U.S. can't believe what they are seeing: a once great country and beacon of freedom turns into a dictatorship.", "url": null, "entities": {"description": {"urls": []}}, "protected": false, "followers_count": 38, "friends_count": 69, "listed_count": 2, "created_at": "Tue Jan 31 15:08:35 +0000 2017", "favourites_count": 374, "utc_offset": null, "time_zone": null, "geo_enabled": false, "verified": false, "statuses_count": 595, "lang": "de", "contributors_enabled": false, "is_translator": false, "is_translation_enabled": false, "profile_background_color": "F5F8FA", "profile_background_image_url": null, "profile_background_image_url_https": null, "profile_background_tile": false, "profile_image_url": "http://pbs.twimg.com/profile_images/826454272434982913/eMvKrVJz_normal.jpg", "profile_image_url_https": "https://pbs.twimg.com/profile_images/826454272434982913/eMvKrVJz_normal.jpg", "profile_link_color": "1DA1F2", "profile_sidebar_border_color": "C0DEED", "profile_sidebar_fill_color": "DDEEF6", "profile_text_color": "333333", "profile_use_background_image": true, "has_extended_profile": false, "default_profile": true, "default_profile_image": false, "following": null, "follow_request_sent": null, "notifications": null, "translator_type": "none"}, "geo": null, "coordinates": null, "place": null, "contributors": null, "retweeted_status": {"created_at": "Wed Mar 08 21:20:23 +0000 2017", "id": 839586620428939264, "id_str": "839586620428939264", "text": "@BarackObama @MichelleObama Mr. Obama, you and Michelle are the classic examples of CLASS! \ud83d\udc4d\ud83c\udffeThank you for respecting all people. Miss you..", "truncated": false, "entities": {"hashtags": [], "symbols": [], "user_mentions": [{"screen_name": "BarackObama", "name": "Barack Obama", "id": 813286, "id_str": "813286", "indices": [0, 12]}, {"screen_name": "MichelleObama", "name": "Michelle Obama", "id": 409486555, "id_str": "409486555", "indices": [13, 27]}], "urls": []}, "metadata": {"iso_language_code": "en", "result_type": "recent"}, "source": "<a href=\"http://twitter.com\" rel=\"nofollow\">Twitter Web Client</a>", "in_reply_to_status_id": 839585255703080968, "in_reply_to_status_id_str": "839585255703080968", "in_reply_to_user_id": 813286, "in_reply_to_user_id_str": "813286", "in_reply_to_screen_name": "BarackObama", "user": {"id": 823762852481732608, "id_str": "823762852481732608", "name": "Countmyblessings\ud83d\ude4f", "screen_name": "vivacioususa", "location": "Boston, MA (USA) ", "description": "\ud83d\udc95Politics/Sushi Lover\ud83d\udc9e[Diehard PATS Fan\ud83d\udc8b](Congratulations New England Patriots!!!\ud83c\uddfa\ud83c\uddf8\ud83c\udfc8~ 5x Super Bowl World Champions.)\ud83c\udfc6\ud83c\udfc6\ud83c\udfc6\ud83c\udfc6\ud83c\udfc6  LET'S GO!!! #OneForTheThumb \ud83d\udc8d \u4e7e\u676f\uff01\ud83c\udf7a\ud83c\udf79\ud83c\udf77", "url": null, "entities": {"description": {"urls": []}}, "protected": false, "followers_count": 300, "friends_count": 1451, "listed_count": 0, "created_at": "Tue Jan 24 05:22:23 +0000 2017", "favourites_count": 7078, "utc_offset": null, "time_zone": null, "geo_enabled": false, "verified": false, "statuses_count": 469, "lang": "en", "contributors_enabled": false, "is_translator": false, "is_translation_enabled": false, "profile_background_color": "000000", "profile_background_image_url": "http://abs.twimg.com/images/themes/theme1/bg.png", "profile_background_image_url_https": "https://abs.twimg.com/images/themes/theme1/bg.png", "profile_background_tile": false, "profile_image_url": "http://pbs.twimg.com/profile_images/823772860040650752/mJ6GDkcc_normal.jpg", "profile_image_url_https": "https://pbs.twimg.com/profile_images/823772860040650752/mJ6GDkcc_normal.jpg", "profile_banner_url": "https://pbs.twimg.com/profile_banners/823762852481732608/1487626670", "profile_link_color": "E81C4F", "profile_sidebar_border_color": "000000", "profile_sidebar_fill_color": "000000", "profile_text_color": "000000", "profile_use_background_image": false, "has_extended_profile": true, "default_profile": false, "default_profile_image": false, "following": null, "follow_request_sent": null, "notifications": null, "translator_type": "none"}, "geo": null, "coordinates": null, "place": null, "contributors": null, "is_quote_status": false, "retweet_count": 5, "favorite_count": 38, "favorited": false, "retweeted": false, "lang": "en"}, "is_quote_status": false, "retweet_count": 5, "favorite_count": 0, "favorited": false, "retweeted": false, "lang": "en"}, "data_point": "none", "time": "Wed Mar 08 22:50:41 +0000 2017"}, "839608942594568193": {"lat": null, "lon": null, "location": "boston", "tweet_id": 839608942594568193, "content": "@TownsendArch nah, but i can get you one of those too-\nObama ACA vs Trump ACA: https://t.co/uhzwnmFHCu", "user": 2918805490, "raw_source": {"created_at": "Wed Mar 08 22:49:05 +0000 2017", "id": 839608942594568193, "id_str": "839608942594568193", "text": "@TownsendArch nah, but i can get you one of those too-\nObama ACA vs Trump ACA: https://t.co/uhzwnmFHCu", "truncated": false, "entities": {"hashtags": [], "symbols": [], "user_mentions": [{"screen_name": "TownsendArch", "name": "Todd Townsend", "id": 1908249498, "id_str": "1908249498", "indices": [0, 13]}], "urls": [], "media": [{"id": 839608873686200320, "id_str": "839608873686200320", "indices": [79, 102], "media_url": "http://pbs.twimg.com/media/C6bj0npU8AAVDmf.jpg", "media_url_https": "https://pbs.twimg.com/media/C6bj0npU8AAVDmf.jpg", "url": "https://t.co/uhzwnmFHCu", "display_url": "pic.twitter.com/uhzwnmFHCu", "expanded_url": "https://twitter.com/killersim00/status/839608942594568193/photo/1", "type": "photo", "sizes": {"medium": {"w": 338, "h": 253, "resize": "fit"}, "large": {"w": 338, "h": 253, "resize": "fit"}, "thumb": {"w": 150, "h": 150, "resize": "crop"}, "small": {"w": 338, "h": 253, "resize": "fit"}}}]}, "extended_entities": {"media": [{"id": 839608873686200320, "id_str": "839608873686200320", "indices": [79, 102], "media_url": "http://pbs.twimg.com/media/C6bj0npU8AAVDmf.jpg", "media_url_https": "https://pbs.twimg.com/media/C6bj0npU8AAVDmf.jpg", "url": "https://t.co/uhzwnmFHCu", "display_url": "pic.twitter.com/uhzwnmFHCu", "expanded_url": "https://twitter.com/killersim00/status/839608942594568193/photo/1", "type": "photo", "sizes": {"medium": {"w": 338, "h": 253, "resize": "fit"}, "large": {"w": 338, "h": 253, "resize": "fit"}, "thumb": {"w": 150, "h": 150, "resize": "crop"}, "small": {"w": 338, "h": 253, "resize": "fit"}}}]}, "metadata": {"iso_language_code": "en", "result_type": "recent"}, "source": "<a href=\"http://twitter.com\" rel=\"nofollow\">Twitter Web Client</a>", "in_reply_to_status_id": 839607662459375619, "in_reply_to_status_id_str": "839607662459375619", "in_reply_to_user_id": 1908249498, "in_reply_to_user_id_str": "1908249498", "in_reply_to_screen_name": "TownsendArch", "user": {"id": 2918805490, "id_str": "2918805490", "name": "Alex Carlson \ud83c\udff3\ufe0f\u200d\ud83c\udf08", "screen_name": "killersim00", "location": "boston", "description": "good candidate for fixie conversion", "url": "https://t.co/sQjmhJsdHX", "entities": {"url": {"urls": [{"url": "https://t.co/sQjmhJsdHX", "expanded_url": "http://www.alexcarlsondesign.com", "display_url": "alexcarlsondesign.com", "indices": [0, 23]}]}, "description": {"urls": []}}, "protected": false, "followers_count": 428, "friends_count": 333, "listed_count": 26, "created_at": "Sat Dec 13 00:45:26 +0000 2014", "favourites_count": 5487, "utc_offset": null, "time_zone": null, "geo_enabled": true, "verified": false, "statuses_count": 5467, "lang": "en", "contributors_enabled": false, "is_translator": false, "is_translation_enabled": false, "profile_background_color": "C0DEED", "profile_background_image_url": "http://abs.twimg.com/images/themes/theme1/bg.png", "profile_background_image_url_https": "https://abs.twimg.com/images/themes/theme1/bg.png", "profile_background_tile": false, "profile_image_url": "http://pbs.twimg.com/profile_images/694970570954428416/F0zLY0zo_normal.jpg", "profile_image_url_https": "https://pbs.twimg.com/profile_images/694970570954428416/F0zLY0zo_normal.jpg", "profile_banner_url": "https://pbs.twimg.com/profile_banners/2918805490/1485616232", "profile_link_color": "1DA1F2", "profile_sidebar_border_color": "C0DEED", "profile_sidebar_fill_color": "DDEEF6", "profile_text_color": "333333", "profile_use_background_image": true, "has_extended_profile": false, "default_profile": true, "default_profile_image": false, "following": null, "follow_request_sent": null, "notifications": null, "translator_type": "none"}, "geo": null, "coordinates": null, "place": null, "contributors": null, "is_quote_status": false, "retweet_count": 0, "favorite_count": 0, "favorited": false, "retweeted": false, "possibly_sensitive": false, "lang": "en"}, "data_point": "none", "time": "Wed Mar 08 22:49:05 +0000 2017"}, "839608548837425157": {"lat": null, "lon": null, "location": "Downingtown, PA", "tweet_id": 839608548837425157, "content": "RT @TheBpDShow: Obama Admininistration's Cyber Warfare against N. Korea's Nuclear Ambitions: https://t.co/oF2FhlhBFB via @YouTube", "user": 2232152180, "raw_source": {"created_at": "Wed Mar 08 22:47:31 +0000 2017", "id": 839608548837425157, "id_str": "839608548837425157", "text": "RT @TheBpDShow: Obama Admininistration's Cyber Warfare against N. Korea's Nuclear Ambitions: https://t.co/oF2FhlhBFB via @YouTube", "truncated": false, "entities": {"hashtags": [], "symbols": [], "user_mentions": [{"screen_name": "TheBpDShow", "name": "Benjamin Dixon \ud83c\udf39", "id": 2949261587, "id_str": "2949261587", "indices": [3, 14]}, {"screen_name": "YouTube", "name": "YouTube", "id": 10228272, "id_str": "10228272", "indices": [121, 129]}], "urls": [{"url": "https://t.co/oF2FhlhBFB", "expanded_url": "http://youtu.be/rMdx_UNeLx4?a", "display_url": "youtu.be/rMdx_UNeLx4?a", "indices": [93, 116]}]}, "metadata": {"iso_language_code": "en", "result_type": "recent"}, "source": "<a href=\"http://twitter.com/download/iphone\" rel=\"nofollow\">Twitter for iPhone</a>", "in_reply_to_status_id": null, "in_reply_to_status_id_str": null, "in_reply_to_user_id": null, "in_reply_to_user_id_str": null, "in_reply_to_screen_name": null, "user": {"id": 2232152180, "id_str": "2232152180", "name": "Roseann Martorana", "screen_name": "RoseannMartora1", "location": "Downingtown, PA", "description": "people planet and peace over profit", "url": null, "entities": {"description": {"urls": []}}, "protected": false, "followers_count": 680, "friends_count": 1195, "listed_count": 127, "created_at": "Thu Dec 05 23:27:55 +0000 2013", "favourites_count": 12348, "utc_offset": null, "time_zone": null, "geo_enabled": true, "verified": false, "statuses_count": 20521, "lang": "en", "contributors_enabled": false, "is_translator": false, "is_translation_enabled": false, "profile_background_color": "C0DEED", "profile_background_image_url": "http://abs.twimg.com/images/themes/theme1/bg.png", "profile_background_image_url_https": "https://abs.twimg.com/images/themes/theme1/bg.png", "profile_background_tile": false, "profile_image_url": "http://pbs.twimg.com/profile_images/834535844702744576/MURhZwsi_normal.jpg", "profile_image_url_https": "https://pbs.twimg.com/profile_images/834535844702744576/MURhZwsi_normal.jpg", "profile_banner_url": "https://pbs.twimg.com/profile_banners/2232152180/1487803826", "profile_link_color": "1DA1F2", "profile_sidebar_border_color": "C0DEED", "profile_sidebar_fill_color": "DDEEF6", "profile_text_color": "333333", "profile_use_background_image": true, "has_extended_profile": false, "default_profile": true, "default_profile_image": false, "following": null, "follow_request_sent": null, "notifications": null, "translator_type": "none"}, "geo": null, "coordinates": null, "place": null, "contributors": null, "retweeted_status": {"created_at": "Wed Mar 08 14:00:27 +0000 2017", "id": 839475905542164481, "id_str": "839475905542164481", "text": "Obama Admininistration's Cyber Warfare against N. Korea's Nuclear Ambitions: https://t.co/oF2FhlhBFB via @YouTube", "truncated": false, "entities": {"hashtags": [], "symbols": [], "user_mentions": [{"screen_name": "YouTube", "name": "YouTube", "id": 10228272, "id_str": "10228272", "indices": [105, 113]}], "urls": [{"url": "https://t.co/oF2FhlhBFB", "expanded_url": "http://youtu.be/rMdx_UNeLx4?a", "display_url": "youtu.be/rMdx_UNeLx4?a", "indices": [77, 100]}]}, "metadata": {"iso_language_code": "en", "result_type": "recent"}, "source": "<a href=\"http://www.google.com/\" rel=\"nofollow\">Google</a>", "in_reply_to_status_id": null, "in_reply_to_status_id_str": null, "in_reply_to_user_id": null, "in_reply_to_user_id_str": null, "in_reply_to_screen_name": null, "user": {"id": 2949261587, "id_str": "2949261587", "name": "Benjamin Dixon \ud83c\udf39", "screen_name": "TheBpDShow", "location": "Boston, MA", "description": "Founder of the @ProgressiveArmy | I don't block trolls. Trolls block me", "url": "https://t.co/UwMg1mFf5n", "entities": {"url": {"urls": [{"url": "https://t.co/UwMg1mFf5n", "expanded_url": "http://www.youtube.com/c/theBenjaminDixonShow", "display_url": "youtube.com/c/theBenjaminD\u2026", "indices": [0, 23]}]}, "description": {"urls": []}}, "protected": false, "followers_count": 28526, "friends_count": 1350, "listed_count": 1525, "created_at": "Mon Dec 29 13:58:38 +0000 2014", "favourites_count": 66193, "utc_offset": null, "time_zone": null, "geo_enabled": false, "verified": false, "statuses_count": 35701, "lang": "en", "contributors_enabled": false, "is_translator": false, "is_translation_enabled": false, "profile_background_color": "000000", "profile_background_image_url": "http://abs.twimg.com/images/themes/theme1/bg.png", "profile_background_image_url_https": "https://abs.twimg.com/images/themes/theme1/bg.png", "profile_background_tile": false, "profile_image_url": "http://pbs.twimg.com/profile_images/834749230015184896/ia30tEd8_normal.jpg", "profile_image_url_https": "https://pbs.twimg.com/profile_images/834749230015184896/ia30tEd8_normal.jpg", "profile_banner_url": "https://pbs.twimg.com/profile_banners/2949261587/1488558167", "profile_link_color": "51597B", "profile_sidebar_border_color": "000000", "profile_sidebar_fill_color": "000000", "profile_text_color": "000000", "profile_use_background_image": false, "has_extended_profile": true, "default_profile": false, "default_profile_image": false, "following": null, "follow_request_sent": null, "notifications": null, "translator_type": "none"}, "geo": null, "coordinates": null, "place": null, "contributors": null, "is_quote_status": false, "retweet_count": 7, "favorite_count": 3, "favorited": false, "retweeted": false, "possibly_sensitive": false, "lang": "en"}, "is_quote_status": false, "retweet_count": 7, "favorite_count": 0, "favorited": false, "retweeted": false, "possibly_sensitive": false, "lang": "en"}, "data_point": "none", "time": "Wed Mar 08 22:47:31 +0000 2017"}, "839608534451040257": {"lat": null, "lon": null, "location": "", "tweet_id": 839608534451040257, "content": "RT @brianjlemieux: @FoxNews @brookefoxnews Thanks Obama", "user": 760254675824185346, "raw_source": {"created_at": "Wed Mar 08 22:47:28 +0000 2017", "id": 839608534451040257, "id_str": "839608534451040257", "text": "RT @brianjlemieux: @FoxNews @brookefoxnews Thanks Obama", "truncated": false, "entities": {"hashtags": [], "symbols": [], "user_mentions": [{"screen_name": "brianjlemieux", "name": "Brian Lemieux", "id": 22387346, "id_str": "22387346", "indices": [3, 17]}, {"screen_name": "FoxNews", "name": "Fox News", "id": 1367531, "id_str": "1367531", "indices": [19, 27]}, {"screen_name": "brookefoxnews", "name": "Brooke Singman", "id": 1098615836, "id_str": "1098615836", "indices": [28, 42]}], "urls": []}, "metadata": {"iso_language_code": "en", "result_type": "recent"}, "source": "<a href=\"https://mobile.twitter.com\" rel=\"nofollow\">Mobile Web (M5)</a>", "in_reply_to_status_id": null, "in_reply_to_status_id_str": null, "in_reply_to_user_id": null, "in_reply_to_user_id_str": null, "in_reply_to_screen_name": null, "user": {"id": 760254675824185346, "id_str": "760254675824185346", "name": "jjbeam22", "screen_name": "jjbeam22", "location": "", "description": "", "url": null, "entities": {"description": {"urls": []}}, "protected": false, "followers_count": 87, "friends_count": 93, "listed_count": 9, "created_at": "Mon Aug 01 23:23:34 +0000 2016", "favourites_count": 12689, "utc_offset": null, "time_zone": null, "geo_enabled": true, "verified": false, "statuses_count": 16222, "lang": "en", "contributors_enabled": false, "is_translator": false, "is_translation_enabled": false, "profile_background_color": "F5F8FA", "profile_background_image_url": null, "profile_background_image_url_https": null, "profile_background_tile": false, "profile_image_url": "http://abs.twimg.com/sticky/default_profile_images/default_profile_0_normal.png", "profile_image_url_https": "https://abs.twimg.com/sticky/default_profile_images/default_profile_0_normal.png", "profile_link_color": "1DA1F2", "profile_sidebar_border_color": "C0DEED", "profile_sidebar_fill_color": "DDEEF6", "profile_text_color": "333333", "profile_use_background_image": true, "has_extended_profile": false, "default_profile": true, "default_profile_image": true, "following": null, "follow_request_sent": null, "notifications": null, "translator_type": "none"}, "geo": null, "coordinates": null, "place": null, "contributors": null, "retweeted_status": {"created_at": "Wed Mar 08 22:30:54 +0000 2017", "id": 839604364318769154, "id_str": "839604364318769154", "text": "@FoxNews @brookefoxnews Thanks Obama", "truncated": false, "entities": {"hashtags": [], "symbols": [], "user_mentions": [{"screen_name": "FoxNews", "name": "Fox News", "id": 1367531, "id_str": "1367531", "indices": [0, 8]}, {"screen_name": "brookefoxnews", "name": "Brooke Singman", "id": 1098615836, "id_str": "1098615836", "indices": [9, 23]}], "urls": []}, "metadata": {"iso_language_code": "en", "result_type": "recent"}, "source": "<a href=\"http://twitter.com/download/iphone\" rel=\"nofollow\">Twitter for iPhone</a>", "in_reply_to_status_id": 839602882336833536, "in_reply_to_status_id_str": "839602882336833536", "in_reply_to_user_id": 1367531, "in_reply_to_user_id_str": "1367531", "in_reply_to_screen_name": "FoxNews", "user": {"id": 22387346, "id_str": "22387346", "name": "Brian Lemieux", "screen_name": "brianjlemieux", "location": "boston\n", "description": "", "url": null, "entities": {"description": {"urls": []}}, "protected": false, "followers_count": 102, "friends_count": 311, "listed_count": 2, "created_at": "Sun Mar 01 18:14:24 +0000 2009", "favourites_count": 138, "utc_offset": -28800, "time_zone": "Pacific Time (US & Canada)", "geo_enabled": false, "verified": false, "statuses_count": 215, "lang": "en", "contributors_enabled": false, "is_translator": false, "is_translation_enabled": false, "profile_background_color": "C0DEED", "profile_background_image_url": "http://abs.twimg.com/images/themes/theme1/bg.png", "profile_background_image_url_https": "https://abs.twimg.com/images/themes/theme1/bg.png", "profile_background_tile": false, "profile_image_url": "http://pbs.twimg.com/profile_images/463147341940527104/7ZCM0ZpY_normal.jpeg", "profile_image_url_https": "https://pbs.twimg.com/profile_images/463147341940527104/7ZCM0ZpY_normal.jpeg", "profile_link_color": "1DA1F2", "profile_sidebar_border_color": "C0DEED", "profile_sidebar_fill_color": "DDEEF6", "profile_text_color": "333333", "profile_use_background_image": true, "has_extended_profile": false, "default_profile": true, "default_profile_image": false, "following": null, "follow_request_sent": null, "notifications": null, "translator_type": "none"}, "geo": null, "coordinates": null, "place": null, "contributors": null, "is_quote_status": false, "retweet_count": 1, "favorite_count": 2, "favorited": false, "retweeted": false, "lang": "en"}, "is_quote_status": false, "retweet_count": 1, "favorite_count": 0, "favorited": false, "retweeted": false, "lang": "en"}, "data_point": "none", "time": "Wed Mar 08 22:47:28 +0000 2017"}, "839608066563792896": {"lat": null, "lon": null, "location": "Cambridge, MA", "tweet_id": 839608066563792896, "content": "I encourage strangers who go \"But Obama!\" to me to review further material on these points with your newfound free time after I block you", "user": 990711, "raw_source": {"created_at": "Wed Mar 08 22:45:36 +0000 2017", "id": 839608066563792896, "id_str": "839608066563792896", "text": "I encourage strangers who go \"But Obama!\" to me to review further material on these points with your newfound free time after I block you", "truncated": false, "entities": {"hashtags": [], "symbols": [], "user_mentions": [], "urls": []}, "metadata": {"iso_language_code": "en", "result_type": "recent"}, "source": "<a href=\"http://twitter.com\" rel=\"nofollow\">Twitter Web Client</a>", "in_reply_to_status_id": 839607740980944896, "in_reply_to_status_id_str": "839607740980944896", "in_reply_to_user_id": 990711, "in_reply_to_user_id_str": "990711", "in_reply_to_screen_name": "JasonT", "user": {"id": 990711, "id_str": "990711", "name": "Jason Tocci", "screen_name": "JasonT", "location": "Cambridge, MA", "description": "Community Manager, Writer/Designer/Researcher, Communication PhD. Opinions are my own and usually pretty nerdy.", "url": null, "entities": {"description": {"urls": []}}, "protected": false, "followers_count": 525, "friends_count": 452, "listed_count": 35, "created_at": "Mon Mar 12 06:09:24 +0000 2007", "favourites_count": 7606, "utc_offset": -18000, "time_zone": "Eastern Time (US & Canada)", "geo_enabled": false, "verified": false, "statuses_count": 22242, "lang": "en", "contributors_enabled": false, "is_translator": false, "is_translation_enabled": false, "profile_background_color": "1A0F0B", "profile_background_image_url": "http://abs.twimg.com/images/themes/theme15/bg.png", "profile_background_image_url_https": "https://abs.twimg.com/images/themes/theme15/bg.png", "profile_background_tile": false, "profile_image_url": "http://pbs.twimg.com/profile_images/660830056915140609/9UbQLV-o_normal.jpg", "profile_image_url_https": "https://pbs.twimg.com/profile_images/660830056915140609/9UbQLV-o_normal.jpg", "profile_banner_url": "https://pbs.twimg.com/profile_banners/990711/1399742389", "profile_link_color": "822900", "profile_sidebar_border_color": "9CCAD6", "profile_sidebar_fill_color": "D1EEF0", "profile_text_color": "364042", "profile_use_background_image": false, "has_extended_profile": false, "default_profile": false, "default_profile_image": false, "following": null, "follow_request_sent": null, "notifications": null, "translator_type": "none"}, "geo": null, "coordinates": null, "place": null, "contributors": null, "is_quote_status": false, "retweet_count": 0, "favorite_count": 1, "favorited": false, "retweeted": false, "lang": "en"}, "data_point": "none", "time": "Wed Mar 08 22:45:36 +0000 2017"}, "839607087881682945": {"lat": null, "lon": null, "location": "Boston, MA", "tweet_id": 839607087881682945, "content": "@TGowdySC AMERICA WONT STOP PUTTING OUT THE TRUTH UNTIL OBAMA,HILLARY AND THE REST GO TO PRISON!", "user": 808011260528852998, "raw_source": {"created_at": "Wed Mar 08 22:41:43 +0000 2017", "id": 839607087881682945, "id_str": "839607087881682945", "text": "@TGowdySC AMERICA WONT STOP PUTTING OUT THE TRUTH UNTIL OBAMA,HILLARY AND THE REST GO TO PRISON!", "truncated": false, "entities": {"hashtags": [], "symbols": [], "user_mentions": [{"screen_name": "TGowdySC", "name": "Trey Gowdy", "id": 237348797, "id_str": "237348797", "indices": [0, 9]}], "urls": []}, "metadata": {"iso_language_code": "en", "result_type": "recent"}, "source": "<a href=\"http://twitter.com\" rel=\"nofollow\">Twitter Web Client</a>", "in_reply_to_status_id": null, "in_reply_to_status_id_str": null, "in_reply_to_user_id": 237348797, "in_reply_to_user_id_str": "237348797", "in_reply_to_screen_name": "TGowdySC", "user": {"id": 808011260528852998, "id_str": "808011260528852998", "name": "kerria kelly", "screen_name": "kerriakelly71", "location": "Boston, MA", "description": "", "url": null, "entities": {"description": {"urls": []}}, "protected": false, "followers_count": 3, "friends_count": 50, "listed_count": 0, "created_at": "Sun Dec 11 18:11:11 +0000 2016", "favourites_count": 0, "utc_offset": null, "time_zone": null, "geo_enabled": false, "verified": false, "statuses_count": 490, "lang": "en", "contributors_enabled": false, "is_translator": false, "is_translation_enabled": false, "profile_background_color": "F5F8FA", "profile_background_image_url": null, "profile_background_image_url_https": null, "profile_background_tile": false, "profile_image_url": "http://abs.twimg.com/sticky/default_profile_images/default_profile_2_normal.png", "profile_image_url_https": "https://abs.twimg.com/sticky/default_profile_images/default_profile_2_normal.png", "profile_link_color": "1DA1F2", "profile_sidebar_border_color": "C0DEED", "profile_sidebar_fill_color": "DDEEF6", "profile_text_color": "333333", "profile_use_background_image": true, "has_extended_profile": true, "default_profile": true, "default_profile_image": true, "following": null, "follow_request_sent": null, "notifications": null, "translator_type": "none"}, "geo": null, "coordinates": null, "place": null, "contributors": null, "is_quote_status": false, "retweet_count": 0, "favorite_count": 0, "favorited": false, "retweeted": false, "lang": "en"}, "data_point": "none", "time": "Wed Mar 08 22:41:43 +0000 2017"}, "839606984810835968": {"lat": null, "lon": null, "location": "Boston, MA", "tweet_id": 839606984810835968, "content": "@SNFonNBC @MSNBC @cnn @FoxNews Good 4 Greatest Team The @Patriots Not as Good as @PresidentTrump_ for @Obama trade for the #GreatestCountry", "user": 2532376551, "raw_source": {"created_at": "Wed Mar 08 22:41:18 +0000 2017", "id": 839606984810835968, "id_str": "839606984810835968", "text": "@SNFonNBC @MSNBC @cnn @FoxNews Good 4 Greatest Team The @Patriots Not as Good as @PresidentTrump_ for @Obama trade for the #GreatestCountry", "truncated": false, "entities": {"hashtags": [{"text": "GreatestCountry", "indices": [123, 139]}], "symbols": [], "user_mentions": [{"screen_name": "SNFonNBC", "name": "SNF on NBC", "id": 167155452, "id_str": "167155452", "indices": [0, 9]}, {"screen_name": "MSNBC", "name": "MSNBC", "id": 2836421, "id_str": "2836421", "indices": [10, 16]}, {"screen_name": "CNN", "name": "CNN", "id": 759251, "id_str": "759251", "indices": [17, 21]}, {"screen_name": "FoxNews", "name": "Fox News", "id": 1367531, "id_str": "1367531", "indices": [22, 30]}, {"screen_name": "Patriots", "name": "New England Patriots", "id": 31126587, "id_str": "31126587", "indices": [56, 65]}, {"screen_name": "PresidentTrump_", "name": "President Trump", "id": 3890345237, "id_str": "3890345237", "indices": [81, 97]}, {"screen_name": "obama", "name": "ob", "id": 246601433, "id_str": "246601433", "indices": [102, 108]}], "urls": []}, "metadata": {"iso_language_code": "en", "result_type": "recent"}, "source": "<a href=\"http://twitter.com/download/android\" rel=\"nofollow\">Twitter for Android</a>", "in_reply_to_status_id": 839596623063838721, "in_reply_to_status_id_str": "839596623063838721", "in_reply_to_user_id": 167155452, "in_reply_to_user_id_str": "167155452", "in_reply_to_screen_name": "SNFonNBC", "user": {"id": 2532376551, "id_str": "2532376551", "name": "BostonStrong", "screen_name": "Cannons513", "location": "Boston, MA", "description": "", "url": null, "entities": {"description": {"urls": []}}, "protected": false, "followers_count": 60, "friends_count": 239, "listed_count": 7, "created_at": "Tue May 06 05:45:25 +0000 2014", "favourites_count": 1382, "utc_offset": null, "time_zone": null, "geo_enabled": false, "verified": false, "statuses_count": 2717, "lang": "en", "contributors_enabled": false, "is_translator": false, "is_translation_enabled": false, "profile_background_color": "C0DEED", "profile_background_image_url": "http://abs.twimg.com/images/themes/theme1/bg.png", "profile_background_image_url_https": "https://abs.twimg.com/images/themes/theme1/bg.png", "profile_background_tile": false, "profile_image_url": "http://pbs.twimg.com/profile_images/465021800393752576/CW8hYZ8C_normal.jpeg", "profile_image_url_https": "https://pbs.twimg.com/profile_images/465021800393752576/CW8hYZ8C_normal.jpeg", "profile_banner_url": "https://pbs.twimg.com/profile_banners/2532376551/1423703305", "profile_link_color": "1DA1F2", "profile_sidebar_border_color": "C0DEED", "profile_sidebar_fill_color": "DDEEF6", "profile_text_color": "333333", "profile_use_background_image": true, "has_extended_profile": true, "default_profile": true, "default_profile_image": false, "following": null, "follow_request_sent": null, "notifications": null, "translator_type": "none"}, "geo": null, "coordinates": null, "place": null, "contributors": null, "is_quote_status": false, "retweet_count": 0, "favorite_count": 0, "favorited": false, "retweeted": false, "lang": "en"}, "data_point": "none", "time": "Wed Mar 08 22:41:18 +0000 2017"}}